[{
    "mediaId": 1,
    "name": "LABELING_PACKAGING",
    "value": "Labeling/Packaging"
}, {
    "mediaId": 2,
    "name": "NEW_PRODUCT_INNOVATION",
    "value": "New Product/innovation"
}, {
    "mediaId": 3,
    "name": "OOH",
    "value": "OOH"
}, {
    "mediaId": 4,
    "name": "PRINT",
    "value": "Print"
}, {
    "mediaId": 5,
    "name": "SOCIAL MEDIA",
    "value": "Social Media"
}, {
    "mediaId": 6,
    "name": "PROMOTIONS",
    "value": "Promotions"
}, {
    "mediaId": 7,
    "name": "RADIO",
    "value": "Radio"
}, {
    "mediaId": 8,
    "name": "SPONSORSHIP",
    "value": "Sponsorship"
}, {
    "mediaId": 9,
    "name": "TVC_OnlineVideos",
    "value": "TVC/Online videos"
}, {
    "mediaId": 10,
    "name": "WEBSITE",
    "value": "Website"
}, {
    "mediaId": 11,
    "name": "OTHERS",
    "value": "Others"
}, {
    "mediaId": 12,
    "name": "COLLABORATION",
    "value": "Collaboration"
}]